.DS_Store
wud/__init__.py
wud/aws.py
wud/football.py
wud/football_team_name.csv
wud/helper.py
wud/linebot.py
wud/scrap.py
wud-0.1.15.dist-info/METADATA
wud-0.1.15.dist-info/WHEEL
wud-0.1.15.dist-info/top_level.txt
wud-0.1.15.dist-info/RECORD
