Metadata-Version: 2.1
Name: wud
Version: 0.1.15
Summary: wud utilities and helpers
Home-page: https://github.com/audreyr/wud
Author: wud
Author-email: audreyr@example.com
License: UNKNOWN
Keywords: wud
Platform: UNKNOWN
Classifier: Development Status :: 2 - Pre-Alpha
Classifier: Intended Audience :: Developers
Classifier: Natural Language :: English
Classifier: Programming Language :: Python :: 3
Classifier: Programming Language :: Python :: 3.5
Classifier: Programming Language :: Python :: 3.6
Classifier: Programming Language :: Python :: 3.7
Classifier: Programming Language :: Python :: 3.8
Requires-Python: >=3.5
